setup.py
NumberAnggi/__init__.py
NumberAnggi/main.py
NumberAnggi.egg-info/PKG-INFO
NumberAnggi.egg-info/SOURCES.txt
NumberAnggi.egg-info/dependency_links.txt
NumberAnggi.egg-info/not-zip-safe
NumberAnggi.egg-info/top_level.txt