Metadata-Version: 2.1
Name: NumberAnggi
Version: 1.2
Summary: Deskripsi angka
Home-page: UNKNOWN
License: UNKNOWN
Platform: UNKNOWN
